README.rst
setup.py
pytidyclub/__init__.py
pytidyclub/pytidyclub.py
pytidyclub.egg-info/PKG-INFO
pytidyclub.egg-info/SOURCES.txt
pytidyclub.egg-info/dependency_links.txt
pytidyclub.egg-info/not-zip-safe
pytidyclub.egg-info/pbr.json
pytidyclub.egg-info/requires.txt
pytidyclub.egg-info/top_level.txt