Metadata-Version: 1.1
Name: pytidyclub
Version: 0.0.6
Summary: A simple Python wrapper for the TidyClub API
Home-page: http://github.com/kyerussell/pytidyclub
Author: Kye Russell
Author-email: me@kye.id.au
License: MIT
Keywords: tidyclub,club,society,api
Platform: UNKNOWN
Classifier: Development Status :: 2 - Pre-Alpha
Classifier: Intended Audience :: Developers
Classifier: License :: OSI Approved :: MIT License
Classifier: Natural Language :: English
Classifier: Programming Language :: Python
Classifier: Topic :: Internet
Classifier: Topic :: Internet :: WWW/HTTP
